tiktokenizer/__init__.py
tiktokenizer/__main__.py
tiktokenizer/cli.py
tiktokenizer/core.py
tiktokenizer-0.1.1.dist-info/METADATA
tiktokenizer-0.1.1.dist-info/WHEEL
tiktokenizer-0.1.1.dist-info/entry_points.txt
tiktokenizer-0.1.1.dist-info/licenses/LICENSE
tiktokenizer-0.1.1.dist-info/RECORD
