Metadata-Version: 2.4
Name: tiktokenizer
Version: 0.1.1
Summary: Convert HuggingFace tokenizers to tiktoken format
Project-URL: Homepage, https://github.com/shakedzy/tiktokenizer
Project-URL: Repository, https://github.com/shakedzy/tiktokenizer
Project-URL: Issues, https://github.com/shakedzy/tiktokenizer/issues
Author: Shaked Zychlinski
License: MIT
License-File: LICENSE
Keywords: huggingface,llm,nlp,tiktoken,tokenizer,transformers
Classifier: Intended Audience :: Developers
Classifier: Intended Audience :: Science/Research
Classifier: License :: OSI Approved :: MIT License
Classifier: Operating System :: OS Independent
Classifier: Programming Language :: Python :: 3
Classifier: Topic :: Scientific/Engineering :: Artificial Intelligence
Classifier: Topic :: Text Processing
Requires-Python: >=3.10
Requires-Dist: tiktoken>=0.12.0
Requires-Dist: transformers>=4.57.3
Provides-Extra: dev
Requires-Dist: pytest>=9.0.2; extra == 'dev'
